LICENSE
MANIFEST.in
README.rst
requirements.txt
setup.py
examples/example.py
ldap_paged_search/__init__.py
ldap_paged_search.egg-info/PKG-INFO
ldap_paged_search.egg-info/SOURCES.txt
ldap_paged_search.egg-info/dependency_links.txt
ldap_paged_search.egg-info/top_level.txt