Metadata-Version: 1.1
Name: ldap-paged-search
Version: 0.4.1
Summary: Easily perform LDAP queries with more than 1000 results
Home-page: https://github.com/neoCrimeLabs/python-ldap_paged_search
Author: Michael Henry a.k.a. neoCrimeLabs
Author-email: mhenry@neocri.me
License: LGPLv2.1
Platform: UNKNOWN
Classifier: Development Status :: 4 - Beta
Classifier: Intended Audience :: Developers
Classifier: License :: OSI Approved :: GNU Lesser General Public License v2 or later (LGPLv2+)
Classifier: Operating System :: OS Independent
Classifier: Programming Language :: Python :: 2
Classifier: Topic :: System :: Systems Administration :: Authentication/Directory :: LDAP
